lie_nn/__init__.py
lie_nn/finite.py
lie_nn/util.py
lie_nn/_src/__init__.py
lie_nn/_src/change_algebra.py
lie_nn/_src/change_algebra_test.py
lie_nn/_src/change_basis.py
lie_nn/_src/clebsch_gordan.py
lie_nn/_src/clebsch_gordan_test.py
lie_nn/_src/conjugate.py
lie_nn/_src/direct_sum.py
lie_nn/_src/finite.py
lie_nn/_src/group_product.py
lie_nn/_src/group_product_test.py
lie_nn/_src/infer_change_of_basis.py
lie_nn/_src/infer_change_of_basis_test.py
lie_nn/_src/irrep.py
lie_nn/_src/irrep_test.py
lie_nn/_src/is_irreducible.py
lie_nn/_src/jax_utils.py
lie_nn/_src/lie_algebra_utils.py
lie_nn/_src/properties.py
lie_nn/_src/real.py
lie_nn/_src/reduce.py
lie_nn/_src/reduce_test.py
lie_nn/_src/reduced_rep.py
lie_nn/_src/reduced_tensor_product.py
lie_nn/_src/reduced_tensor_product_test.py
lie_nn/_src/rep.py
lie_nn/_src/tensor_product.py
lie_nn/_src/tensor_product_test.py
lie_nn/_src/util.py
lie_nn/_src/util_test.py
lie_nn/_src/discrete_groups/__init__.py
lie_nn/_src/discrete_groups/perm.py
lie_nn/_src/irreps/__init__.py
lie_nn/_src/irreps/o3_real.py
lie_nn/_src/irreps/sl2c.py
lie_nn/_src/irreps/so13.py
lie_nn/_src/irreps/so13_test.py
lie_nn/_src/irreps/so3_real.py
lie_nn/_src/irreps/son.py
lie_nn/_src/irreps/spn.py
lie_nn/_src/irreps/su2.py
lie_nn/_src/irreps/su2_real.py
lie_nn/_src/irreps/sun.py
lie_nn/_src/irreps/sun_test.py
lie_nn/_src/irreps/z2.py
lie_nn/irreps/__init__.py
lie_nn-0.0.0.dist-info/LICENSE
lie_nn-0.0.0.dist-info/METADATA
lie_nn-0.0.0.dist-info/WHEEL
lie_nn-0.0.0.dist-info/top_level.txt
lie_nn-0.0.0.dist-info/RECORD
