Metadata-Version: 2.1
Name: lie-nn
Version: 0.0.0
Summary: Tensor Products for Lie Groups.
Home-page: https://github.com/lie-nn/lie-nn
License: MIT License
Platform: UNKNOWN
Classifier: Programming Language :: Python :: 3.7
Requires-Python: >=3.7
Requires-Dist: numpy
Requires-Dist: scipy
Requires-Dist: multipledispatch
